claude_statusline/__init__.py
claude_statusline/__main__.py
claude_statusline/activity_heatmap.py
claude_statusline/analytics_cli.py
claude_statusline/budget_manager.py
claude_statusline/cli.py
claude_statusline/config.json
claude_statusline/console_utils.py
claude_statusline/cost_analyzer.py
claude_statusline/daemon.py
claude_statusline/daemon_manager.py
claude_statusline/daily_report.py
claude_statusline/data_directory_utils.py
claude_statusline/health_monitor.py
claude_statusline/instance_manager.py
claude_statusline/interactive_theme_manager.py
claude_statusline/model_usage.py
claude_statusline/prices.json
claude_statusline/rebuild.py
claude_statusline/safe_file_operations.py
claude_statusline/session_analyzer.py
claude_statusline/simple_theme_selector.py
claude_statusline/statusline.py
claude_statusline/statusline_rotator.py
claude_statusline/summary_report.py
claude_statusline/trend_analyzer.py
claude_statusline/unified_powerline_system.py
claude_statusline/update_prices.py
claude_statusline/verify_costs.py
claude_statusline-1.9.1.dist-info/licenses/LICENSE
claude_statusline-1.9.1.dist-info/METADATA
claude_statusline-1.9.1.dist-info/WHEEL
claude_statusline-1.9.1.dist-info/entry_points.txt
claude_statusline-1.9.1.dist-info/top_level.txt
claude_statusline-1.9.1.dist-info/RECORD
