Metadata-Version: 2.4
Name: claude-statusline
Version: 1.9.1
Summary: Real-time session tracking and analytics for Claude Code
Home-page: https://github.com/ersinkoc/claude-statusline
Author: Ersin Koç
Author-email: Ersin Koç <ersinkoc@gmail.com>
License: MIT
Project-URL: Homepage, https://github.com/ersinkoc/claude-statusline
Project-URL: Documentation, https://github.com/ersinkoc/claude-statusline/blob/main/README.md
Project-URL: Repository, https://github.com/ersinkoc/claude-statusline
Project-URL: Bug Tracker, https://github.com/ersinkoc/claude-statusline/issues
Project-URL: Changelog, https://github.com/ersinkoc/claude-statusline/blob/main/CHANGELOG.md
Keywords: claude,claude-code,statusline,monitoring,analytics,ai,anthropic,session-tracking,cost-tracking,developer-tools
Classifier: Development Status :: 4 - Beta
Classifier: Intended Audience :: Developers
Classifier: Topic :: Software Development :: Libraries :: Python Modules
Classifier: Topic :: System :: Monitoring
Classifier: Topic :: Utilities
Classifier: License :: OSI Approved :: MIT License
Classifier: Programming Language :: Python :: 3
Classifier: Programming Language :: Python :: 3.8
Classifier: Programming Language :: Python :: 3.9
Classifier: Programming Language :: Python :: 3.10
Classifier: Programming Language :: Python :: 3.11
Classifier: Programming Language :: Python :: 3.12
Classifier: Operating System :: OS Independent
Classifier: Environment :: Console
Requires-Python: >=3.8
License-File: LICENSE
Requires-Dist: psutil>=5.9.0
Requires-Dist: colorama>=0.4.6
Provides-Extra: dev
Requires-Dist: pytest>=7.0; extra == "dev"
Requires-Dist: pytest-cov>=4.0; extra == "dev"
Requires-Dist: black>=23.0; extra == "dev"
Requires-Dist: flake8>=6.0; extra == "dev"
Requires-Dist: mypy>=1.0; extra == "dev"
Requires-Dist: build>=0.10; extra == "dev"
Requires-Dist: twine>=4.0; extra == "dev"
Dynamic: author
Dynamic: home-page
Dynamic: license-file
Dynamic: requires-python
